[
    {
        "char_id": 1,
        "name": "hj song",
        "birthday": "09-07-1958",
        "occupation": [
            "Housewife",
            "Clepto"
        ],
        "img": "https://images.generated.photos/RLHFWsxXKojnhXzWmUze6BJ2X351-H5NsT25gHG8Nog/rs:fit:512:512/wm:0.95:sowe:18:18:0.33/czM6Ly9pY29uczgu/Z3Bob3Rvcy1wcm9k/LnBob3Rvcy92M18w/MDQxNjUzLmpwZw.jpg",
        "status": "still alive",
        "nickname": "shj",
        "appearance": [
            1,
            2,
            3,
            4,
            5
        ],
        "portrayed": "Bryan Cranston",
        "category": "Breaking Bad",
        "better_call_saul_appearance": []
    },
    {
        "char_id": 2,
        "name": "Jesse Pinkman",
        "birthday": "09-24-1984",
        "occupation": [
            "High School Chemistry Teacher",
            "Meth King Pin"
        ],
        "img": "https://vignette.wikia.nocookie.net/breakingbad/images/9/95/JesseS5.jpg/revision/latest?cb=20120620012441",
        "status": "Alive",
        "nickname": "Cap n' Cook",
        "appearance": [
            1,
            2,
            3,
            4,
            5
        ],
        "portrayed": "Aaron Paul",
        "category": "Breaking Bad",
        "better_call_saul_appearance": []
    }
]
